CHANGELOG.md
CONTRIBUTING.md
LICENSE.txt
MANIFEST.in
README.md
setup.py
distribute/icepapcms.desktop
icepapcms/__init__.py
icepapcms/__main__.py
icepapcms/helpers.py
icepapcms.egg-info/PKG-INFO
icepapcms.egg-info/SOURCES.txt
icepapcms.egg-info/dependency_links.txt
icepapcms.egg-info/entry_points.txt
icepapcms.egg-info/requires.txt
icepapcms.egg-info/top_level.txt
icepapcms/db/__init__.py
icepapcms/db/creates-mysql.sql
icepapcms/db/creates_sqlite.sql
icepapcms/db/db_notes.txt
icepapcms/db/dbmodel.mwb
icepapcms/db/mysql-to-sqlite.sh
icepapcms/doc/IcePAP_HardwareManual.pdf
icepapcms/doc/IcePAP_UserManual-1.0b-150526-fw3.11+.pdf
icepapcms/doc/IcePAP_UserManual.pdf
icepapcms/doc/IcePAP_UserManual_last.pdf
icepapcms/doc/IcePAP_UserManual_working.pdf
icepapcms/doc/IcepapCMSUserManual.pdf
icepapcms/doc/Icepapicon.png
icepapcms/doc/__init__.py
icepapcms/doc/remoteserver_setup.txt
icepapcms/gui/__init__.py
icepapcms/gui/dialogaddicepap.py
icepapcms/gui/dialogaddlocation.py
icepapcms/gui/dialogconflictdriver_expert.py
icepapcms/gui/dialogconflictdriver_nonexpert.py
icepapcms/gui/dialogdriverconflict.py
icepapcms/gui/dialoghomesrch.py
icepapcms/gui/dialogipapprogram.py
icepapcms/gui/dialognewdriver.py
icepapcms/gui/dialogpreferences.py
icepapcms/gui/dialogsnapshot.py
icepapcms/gui/historiccfgwidget.py
icepapcms/gui/icepap_treemodel.py
icepapcms/gui/icepapcms.py
icepapcms/gui/icepapdriverwidget.py
icepapcms/gui/ipapconsole.py
icepapcms/gui/messagedialogs.py
icepapcms/gui/pageipapcrate.py
icepapcms/gui/pageipapdriver.py
icepapcms/gui/pageipapsystem.py
icepapcms/gui/pyconsoletext.py
icepapcms/gui/qvalidatelineedit.py
icepapcms/gui/templatescatalogwidget.py
icepapcms/gui/Led/Led.py
icepapcms/gui/Led/__init__.py
icepapcms/gui/Led/images24/__init__.py
icepapcms/gui/Led/images24/ledblue.png
icepapcms/gui/Led/images24/ledblueoff.png
icepapcms/gui/Led/images24/ledgreen.png
icepapcms/gui/Led/images24/ledgreenoff.png
icepapcms/gui/Led/images24/ledorange.png
icepapcms/gui/Led/images24/ledorangeoff.png
icepapcms/gui/Led/images24/ledred.png
icepapcms/gui/Led/images24/ledredoff.png
icepapcms/gui/Led/images24/ledyellow.png
icepapcms/gui/Led/images24/ledyellowoff.png
